HISTORY.txt
README.txt
setup.cfg
setup.py
jyu/__init__.py
jyu.z3cform.datepicker.egg-info/PKG-INFO
jyu.z3cform.datepicker.egg-info/SOURCES.txt
jyu.z3cform.datepicker.egg-info/dependency_links.txt
jyu.z3cform.datepicker.egg-info/entry_points.txt
jyu.z3cform.datepicker.egg-info/namespace_packages.txt
jyu.z3cform.datepicker.egg-info/not-zip-safe
jyu.z3cform.datepicker.egg-info/requires.txt
jyu.z3cform.datepicker.egg-info/top_level.txt
jyu/z3cform/__init__.py
jyu/z3cform/datepicker/__init__.py
jyu/z3cform/datepicker/configure.zcml
jyu/z3cform/datepicker/upgrades.py
jyu/z3cform/datepicker/upgrades.pyc
jyu/z3cform/datepicker/upgrades.zcml
jyu/z3cform/datepicker/viewlets.py
jyu/z3cform/datepicker/profiles/default/cssregistry.xml
jyu/z3cform/datepicker/profiles/default/jsregistry.xml
jyu/z3cform/datepicker/profiles/default/metadata.xml
jyu/z3cform/datepicker/profiles/upgrade1to2/cssregistry.xml
jyu/z3cform/datepicker/profiles/upgrade1to2/jsregistry.xml
jyu/z3cform/datepicker/profiles/upgrade1to2/metadata.xml
jyu/z3cform/datepicker/static/jquery.datepick-af.js
jyu/z3cform/datepicker/static/jquery.datepick-ar.js
jyu/z3cform/datepicker/static/jquery.datepick-az.js
jyu/z3cform/datepicker/static/jquery.datepick-bg.js
jyu/z3cform/datepicker/static/jquery.datepick-bs.js
jyu/z3cform/datepicker/static/jquery.datepick-ca.js
jyu/z3cform/datepicker/static/jquery.datepick-cs.js
jyu/z3cform/datepicker/static/jquery.datepick-da.js
jyu/z3cform/datepicker/static/jquery.datepick-de-CH.js
jyu/z3cform/datepicker/static/jquery.datepick-de.js
jyu/z3cform/datepicker/static/jquery.datepick-el.js
jyu/z3cform/datepicker/static/jquery.datepick-en-GB.js
jyu/z3cform/datepicker/static/jquery.datepick-eo.js
jyu/z3cform/datepicker/static/jquery.datepick-es-AR.js
jyu/z3cform/datepicker/static/jquery.datepick-es.js
jyu/z3cform/datepicker/static/jquery.datepick-et.js
jyu/z3cform/datepicker/static/jquery.datepick-eu.js
jyu/z3cform/datepicker/static/jquery.datepick-fa.js
jyu/z3cform/datepicker/static/jquery.datepick-fi.js
jyu/z3cform/datepicker/static/jquery.datepick-fo.js
jyu/z3cform/datepicker/static/jquery.datepick-fr-CH.js
jyu/z3cform/datepicker/static/jquery.datepick-fr.js
jyu/z3cform/datepicker/static/jquery.datepick-gl.js
jyu/z3cform/datepicker/static/jquery.datepick-gu.js
jyu/z3cform/datepicker/static/jquery.datepick-he.js
