Metadata-Version: 1.0
Name: jyu.z3cform.datepicker
Version: 1.0b12
Summary: Integrates Keith Wood's jQuery Datepicker for z3c.form on Plone.
Home-page: http://pypi.python.org/pypi/jyu.z3cform.datepicker
Author: Asko Soukka
Author-email: asko.soukka@iki.fi
License: GPL
Platform: UNKNOWN
Classifier: Programming Language :: Python
Classifier: Topic :: Software Development :: Libraries :: Python Modules
